CHANGES.rst
LICENSE
MANIFEST.in
README.rst
bootstrap.py
buildout.cfg
checkouts.cfg
deployment.cfg
development.ini
dokku.cfg
jenkins.cfg
production.ini
setup.cfg
setup.py
sources.cfg
versions.cfg
daceui/__init__.py
daceui/interfaces.py
daceui/layout.py
daceui/processes.py
daceui/util.py
daceui/views.py
daceui/static/behaviors.local.js
daceui/static/jquery.infinitescroll.js
daceui/static/css/dace_ui.css
daceui/static/dygraph/dygraph-combined.js
daceui/static/flot/API.md
daceui/static/flot/CONTRIBUTING.md
daceui/static/flot/FAQ.md
daceui/static/flot/LICENSE.txt
daceui/static/flot/Makefile
daceui/static/flot/NEWS.md
daceui/static/flot/PLUGINS.md
daceui/static/flot/README.md
daceui/static/flot/excanvas.js
daceui/static/flot/excanvas.min.js
daceui/static/flot/jquery.colorhelpers.js
daceui/static/flot/jquery.colorhelpers.min.js
daceui/static/flot/jquery.flot.canvas.js
daceui/static/flot/jquery.flot.canvas.min.js
daceui/static/flot/jquery.flot.categories.js
daceui/static/flot/jquery.flot.categories.min.js
daceui/static/flot/jquery.flot.crosshair.js
daceui/static/flot/jquery.flot.crosshair.min.js
daceui/static/flot/jquery.flot.errorbars.js
daceui/static/flot/jquery.flot.errorbars.min.js
daceui/static/flot/jquery.flot.fillbetween.js
daceui/static/flot/jquery.flot.fillbetween.min.js
daceui/static/flot/jquery.flot.image.js
daceui/static/flot/jquery.flot.image.min.js
daceui/static/flot/jquery.flot.js
daceui/static/flot/jquery.flot.min.js
daceui/static/flot/jquery.flot.navigate.js
daceui/static/flot/jquery.flot.navigate.min.js
daceui/static/flot/jquery.flot.pie.js
daceui/static/flot/jquery.flot.pie.min.js
daceui/static/flot/jquery.flot.resize.js
daceui/static/flot/jquery.flot.resize.min.js
daceui/static/flot/jquery.flot.selection.js
daceui/static/flot/jquery.flot.selection.min.js
daceui/static/flot/jquery.flot.stack.js
daceui/static/flot/jquery.flot.stack.min.js
daceui/static/flot/jquery.flot.symbol.js
daceui/static/flot/jquery.flot.symbol.min.js
ecreall_daceui.egg-info/PKG-INFO
ecreall_daceui.egg-info/SOURCES.txt
ecreall_daceui.egg-info/dependency_links.txt
ecreall_daceui.egg-info/entry_points.txt
ecreall_daceui.egg-info/not-zip-safe
ecreall_daceui.egg-info/requires.txt
ecreall_daceui.egg-info/top_level.txt